LICENSE
README.md
authorization.json
setup.py
OntimDevTool/__init__.py
OntimDevTool/__main__.py
OntimDevTool/auth_controller.py
OntimDevTool/diag_port_controller.py
OntimDevTool/login_ui.py
OntimDevTool/main.py
OntimDevTool/main_ui.py
otdev_tool.egg-info/PKG-INFO
otdev_tool.egg-info/SOURCES.txt
otdev_tool.egg-info/dependency_links.txt
otdev_tool.egg-info/entry_points.txt
otdev_tool.egg-info/requires.txt
otdev_tool.egg-info/top_level.txt