Metadata-Version: 2.1
Name: otdev-tool
Version: 2.0.1
Summary: Dev tools of Ontim.
Home-page: http://example.com
Author: caiyongqing
Author-email: yongqing.cai@chino-e.com
License: UNKNOWN
Platform: UNKNOWN
Classifier: License :: OSI Approved :: MIT License
Classifier: Intended Audience :: Developers
Classifier: Operating System :: OS Independent
Classifier: Programming Language :: Python :: 3 :: Only
Classifier: Programming Language :: Python :: 3.6
Classifier: Programming Language :: Python :: 3.7
Classifier: Programming Language :: Python :: 3.8
License-File: LICENSE
